{"correlationId":"bcb2dc0e-737f-4aed-82cc-6d960bc02806","message":{"exportTimeStamp":"2020-06-18T03:00:02.587894Z","companyId":"blueenergy","id":"bcb2dc0e-737f-4aed-82cc-6d960bc02806","externalId":null,"customerReference":"2019/05/05","vessel":{"imo":"9308728","name":"Bakkedal"},"company":{"id":"blueenergy","displayName":"Blue Energy"},"laycan":{"start":"2019-04-19T00:00:00+08:00","end":"2019-04-28T23:59:59+08:00"},"source":"WEB","editable":true,"cargoLines":[{"cargoLineId":"92e88ac2-383a-4781-9fac-63a1774d99ad","receiver":"blueenergy","customerReference":"2019/05/05","material":{"materialId":"D54AE516-C044-4556-9371-2A9732C4B03B","name":"COAL HIGH SULFUR"},"quantity":{"expected":50000.0,"confirmed":50000.0},"loadTerminalCall":{"terminalCallId":"040bc75a-e4c6-4db3-9abc-e13898a61dd4","eta":{"calculated":"2019-04-23T12:00:00+08:00","expected":null,"confirmed":"2019-04-23T12:00:00+08:00"},"etb":{"calculated":"2019-04-23T12:00:00+08:00","expected":null,"confirmed":"2019-04-23T12:00:00+08:00"},"etd":{"calculated":"2019-04-25T12:00:00+08:00","expected":null,"confirmed":"2019-04-25T12:00:00+08:00"},"action":"LOAD","port":{"portId":"IDTAB","companyPortName":null,"name":"Taboneo","terminalId":"8b72fa24-0eae-456e-b77f-18199da6f7b7","timezone":"Asia/Makassar","position":{"lat":-3.332106,"lon":114.55165}},"confirmed":true},"dischargeTerminalCall":{"terminalCallId":"91389d97-3576-48ec-9934-6b016f224408","eta":{"calculated":"2019-05-05T12:00:00+08:00","expected":null,"confirmed":"2019-05-05T12:00:00+08:00"},"etb":{"calculated":"2019-05-05T12:00:00+08:00","expected":null,"confirmed":"2019-05-05T12:00:00+08:00"},"etd":{"calculated":"2019-05-07T12:00:00+08:00","expected":null,"confirmed":"2019-05-07T12:00:00+08:00"},"action":"DISCHARGE","port":{"portId":"PHBTG","companyPortName":null,"name":"Batangas","terminalId":"7be258eb-92e5-455d-8164-d38b77fd97ba","timezone":"Asia/Manila","position":{"lat":13.75,"lon":121.05}},"confirmed":true},"permission":"EDIT","delivered":true,"outboundDelivered":true}],"modified":"2019-05-13T10:06:30.110643Z","modifiedBy":"A********r S*****y","permission":"EDIT","delivered":true,"outboundDelivered":true,"demurrage":null,"counterpart":null}}